django_selectize/__init__.py
django_selectize/forms.py
django_selectize/static/django_selectize/django_selectize.js
django_selectize/static/django_selectize/selectize.css
django_selectize/static/django_selectize/selectize.min.js
django_selectize-2.0.dist-info/LICENSE
django_selectize-2.0.dist-info/METADATA
django_selectize-2.0.dist-info/WHEEL
django_selectize-2.0.dist-info/top_level.txt
django_selectize-2.0.dist-info/RECORD
