Metadata-Version: 2.1
Name: django-selectize
Version: 2.0
Summary: django-selectize is a Django app based on Selectize.js that help you to create Select and Multiselect widgets in Django forms.
Home-page: https://github.com/djangoer/django-selectize
Author: Suhail VS
Author-email: suhailvs@gmail.com
Project-URL: Bug Tracker, https://github.com/djangoer/django-selectize/issues
Classifier: Programming Language :: Python :: 3
Classifier: Programming Language :: Python :: 3.8
Classifier: Programming Language :: Python :: 3.9
Classifier: License :: OSI Approved :: MIT License
Classifier: Operating System :: OS Independent
Requires-Python: >=3.6
License-File: LICENSE
Requires-Dist: django (>=3.2)
